dikshant_password_tool-0.1.1.dist-info/licenses/LICENSE.txt
password_generator/__init__.py
password_generator/generator.py
dikshant_password_tool-0.1.1.dist-info/METADATA
dikshant_password_tool-0.1.1.dist-info/WHEEL
dikshant_password_tool-0.1.1.dist-info/top_level.txt
dikshant_password_tool-0.1.1.dist-info/RECORD
